{
  "about": {
      "title": "About", 
      "body": [
        "This Page is under construction. ",
        "We are working hard to make it happen.",
        "Thank you for your interests."
      ]
  },
  "team": {
    "title": "Team", 
    "body": [
      "This Page is under construction. ",
      "We are working hard to make it happen.",
      "Thank you for your interests."
    ]
  },
  "why": {
    "title": "Why", 
    "body": [
      "This Page is under construction. ",
      "We are working hard to make it happen.",
      "Thank you for your interests."
    ]
  },
  "faq": {
    "title": "Frequently Asked Questions", 
    "body": [
      "This Page is under construction. ",
      "We are working hard to make it happen.",
      "Thank you for your interests."
    ]
  },
  "disclaimers": {
    "title": "Disclaimers", 
    "body": [
      "This Page is under construction. ",
      "We are working hard to make it happen.",
      "Thank you for your interests."
    ]
  },
  "branding": {
    "title": "Branding", 
    "body": [
      "This Page is under construction. ",
      "We are working hard to make it happen.",
      "Thank you for your interests."
    ]
  },
  "privacy": {
    "title": "Privacy", 
    "body": [
      "This Page is under construction. ",
      "We are working hard to make it happen.",
      "Thank you for your interests."
    ]
  },
  "tos": {
    "title": "Terms of Use", 
    "body": [
      "This Page is under construction. ",
      "We are working hard to make it happen.",
      "Thank you for your interests."
    ]
  }
}
